httpr/__init__.py
httpr/httpr.abi3.so
httpr/httpr.pyi
httpr/py.typed
httpr-0.3.3.dist-info/METADATA
httpr-0.3.3.dist-info/WHEEL
httpr-0.3.3.dist-info/licenses/LICENSE
httpr-0.3.3.dist-info/RECORD
