Metadata-Version: 2.4
Name: httpr
Version: 0.3.3
Classifier: Programming Language :: Rust
Classifier: Programming Language :: Python :: 3
Classifier: Programming Language :: Python :: 3 :: Only
Classifier: Programming Language :: Python :: 3.9
Classifier: Programming Language :: Python :: 3.10
Classifier: Programming Language :: Python :: 3.11
Classifier: Programming Language :: Python :: 3.12
Classifier: Programming Language :: Python :: 3.13
Classifier: Programming Language :: Python :: Implementation :: CPython
Classifier: Programming Language :: Python :: Implementation :: PyPy
Classifier: Topic :: Internet :: WWW/HTTP
Classifier: Topic :: Software Development :: Libraries :: Python Modules
Requires-Dist: matplotlib ; extra == 'benchmark'
Requires-Dist: pandas ; extra == 'benchmark'
Requires-Dist: starlette ; extra == 'benchmark'
Requires-Dist: uvicorn ; extra == 'benchmark'
Requires-Dist: requests ; extra == 'benchmark'
Requires-Dist: httpx ; extra == 'benchmark'
Requires-Dist: tls-client ; extra == 'benchmark'
Requires-Dist: curl-cffi ; extra == 'benchmark'
Requires-Dist: pycurl ; extra == 'benchmark'
Requires-Dist: typing-extensions ; extra == 'benchmark'
Requires-Dist: aiohttp ; extra == 'benchmark'
Requires-Dist: cbor2 ; extra == 'benchmark'
Requires-Dist: jupyter ; extra == 'benchmark'
Requires-Dist: ipykernel ; extra == 'benchmark'
Requires-Dist: gunicorn ; extra == 'benchmark'
Requires-Dist: fastapi ; extra == 'benchmark'
Requires-Dist: certifi ; extra == 'dev'
Requires-Dist: pytest>=8.1.1 ; extra == 'dev'
Requires-Dist: pytest-asyncio>=0.25.3 ; extra == 'dev'
Requires-Dist: pytest-benchmark>=5.1.0 ; extra == 'dev'
Requires-Dist: pytest-httpbin>=2.1.0 ; extra == 'dev'
Requires-Dist: typing-extensions ; python_full_version < '3.12' and extra == 'dev'
Requires-Dist: mypy>=1.14.1 ; extra == 'dev'
Requires-Dist: ruff>=0.9.2 ; extra == 'dev'
Requires-Dist: maturin ; extra == 'dev'
Requires-Dist: trustme ; extra == 'dev'
Requires-Dist: cbor2 ; extra == 'dev'
Requires-Dist: go-task-bin ; extra == 'dev'
Requires-Dist: pre-commit ; extra == 'dev'
Requires-Dist: mkdocs-material[imaging] ; extra == 'docs'
Requires-Dist: mkdocstrings[python]>=0.27.0 ; extra == 'docs'
Requires-Dist: mkdocs-gen-files ; extra == 'docs'
Requires-Dist: mkdocs-literate-nav ; extra == 'docs'
Requires-Dist: mkdocs-llmstxt ; extra == 'docs'
Provides-Extra: benchmark
Provides-Extra: dev
Provides-Extra: docs
License-File: LICENSE
Summary: Fast HTTP client for Python
Keywords: python,request
Author: thomasht86
License: MIT License
Requires-Python: >=3.9
